escapy/__init__.py
escapy/__main__.py
escapy/commons.py
escapy/config_parser.py
escapy/fonts.py
escapy/grammar.py
escapy/parser.py
escapy/user_defined_characters.py
escapy/data/escapy.conf
escapy/encodings/__init__.py
escapy/encodings/abicomp.py
escapy/encodings/brascii.py
escapy/encodings/cp774.py
escapy/encodings/i18n_codecs.py
escapy/encodings/iscii.py
escapy/encodings/mazovia.py
escapy/encodings/ram_codec.py
pyscape-1.0.1.dist-info/LICENSE
pyscape-1.0.1.dist-info/METADATA
pyscape-1.0.1.dist-info/WHEEL
pyscape-1.0.1.dist-info/entry_points.txt
pyscape-1.0.1.dist-info/top_level.txt
pyscape-1.0.1.dist-info/RECORD
