Metadata-Version: 2.1
Name: pyscape
Version: 1.0.1
Summary: An advanced Python interpreter for ESC/P and ESC/P2 commands, efficiently and accurately converting your print workflows into precise vectorial PDFs.
Home-page: https://github.com/ysard/escapy
Author: Ysard
Author-email: ysard_git@gmx.fr
Keywords: printer,dotmatrix,escp2,escp,pdf
Classifier: Development Status :: 5 - Production/Stable
Classifier: Intended Audience :: End Users/Desktop
Classifier: Intended Audience :: System Administrators
Classifier: Programming Language :: Python :: 3
Classifier: Programming Language :: Python :: 3.10
Classifier: Programming Language :: Python :: 3.11
Classifier: Programming Language :: Python :: 3.12
Classifier: Programming Language :: Python :: 3.13
Classifier: License :: OSI Approved :: GNU Affero General Public License v3 or later (AGPLv3+)
Requires-Python: >=3.10
License-File: LICENSE
Requires-Dist: reportlab[accel] <5.0,>=4.0
Requires-Dist: lark <2.0,>=1.2.2
Requires-Dist: numpy >=1.26.0
Requires-Dist: platformdirs <5.0,>=4.1.0
Requires-Dist: pillow
Provides-Extra: dev
Requires-Dist: pytest-cov >=2.6.1 ; extra == 'dev'
Requires-Dist: pytest >=6.2.0 ; extra == 'dev'
Requires-Dist: zest.releaser[recommended] ; extra == 'dev'
Requires-Dist: coverage-badge ; extra == 'dev'
Requires-Dist: prospector ; extra == 'dev'
Requires-Dist: pyroma ; extra == 'dev'
Requires-Dist: check-manifest ; extra == 'dev'
Provides-Extra: doc
Requires-Dist: sphinx ; extra == 'doc'
Requires-Dist: sphinx-rtd-theme >=1.0.0 ; extra == 'doc'
Requires-Dist: sphinx-argparse ; extra == 'doc'
